LICENSE
MANIFEST.in
README
setup.py
deep_personality.egg-info/PKG-INFO
deep_personality.egg-info/SOURCES.txt
deep_personality.egg-info/dependency_links.txt
deep_personality.egg-info/top_level.txt
dpcv/__init__.py
dpcv/checkpoint/__init__.py
dpcv/checkpoint/load.py
dpcv/checkpoint/save.py
dpcv/config/__init__.py
dpcv/config/audiovisual_resnet_cfg.py
dpcv/config/bi_modal_lstm_cfg.py
dpcv/config/crnet_cfg.py
dpcv/config/deep_bimodal_regression_cfg.py
dpcv/config/default_cfg.py
dpcv/config/default_config_opt.py
dpcv/config/hrnet_cls_cfg.py
dpcv/config/interpret_aud_cfg.py
dpcv/config/interpret_dan_cfg.py
dpcv/config/per_emo_cfg.py
dpcv/config/resnet_3d_cfg.py
dpcv/config/senet_cfg.py
dpcv/config/slow_fast_cfg.py
dpcv/config/swin_transformer_cfg.py
dpcv/config/tpn_cfg.py
dpcv/config/vat_cfg.py
dpcv/data/__init__.py
dpcv/data/datasets/__init__.py
dpcv/data/datasets/audio_data.py
dpcv/data/datasets/audio_visual_data.py
dpcv/data/datasets/bi_modal_data.py
dpcv/data/datasets/build.py
dpcv/data/datasets/common.py
dpcv/data/datasets/cr_data.py
dpcv/data/datasets/feature_extract_dataset.py
dpcv/data/datasets/feature_extract_true_personality_dataset.py
dpcv/data/datasets/interpretability_audio_data.py
dpcv/data/datasets/multi_modal_pred.py
dpcv/data/datasets/pers_emo_data.py
dpcv/data/datasets/second_stage_dataset.py
dpcv/data/datasets/slow_fast_data.py
dpcv/data/datasets/slow_fast_data_true_personality.py
dpcv/data/datasets/temporal_data.py
dpcv/data/datasets/tpn_data.py
dpcv/data/datasets/ture_personality_data.py
dpcv/data/datasets/vat_data.py
dpcv/data/datasets/video_frame_data.py
dpcv/data/datasets/video_segment_data.py
dpcv/data/dynamicimage/__init__.py
dpcv/data/dynamicimage/example.py
dpcv/data/face_extract/__init__.py
dpcv/data/face_extract/face_detector.py
dpcv/data/face_extract/face_img_extractor.py
dpcv/data/transforms/__init__.py
dpcv/data/transforms/build.py
dpcv/data/transforms/spatial_transforms.py
dpcv/data/transforms/temporal_transforms.py
dpcv/data/transforms/transform.py
dpcv/data/utils/__init__.py
dpcv/data/utils/feature_extractor.py
dpcv/data/utils/feature_extractor_tp.py
dpcv/data/utils/logfbank_feat_from_wav.py
