Metadata-Version: 2.1
Name: deep-personality
Version: 0.1.4
Summary: an open source bench mark for automatic personality recognition
Home-page: https://testpypi.python.org/pypi/deep_personality
Author: LiaoRongFan, SongSiYang
Author-email: rongfan.liao@hotmail.com
License: LICENSE
Platform: UNKNOWN
License-File: LICENSE
